CHANGES.txt
LICENSE-2.0.txt
MANIFEST.in
README.rst
contributors.txt
setup.py
metavariant/__init__.py
metavariant/components.py
metavariant/config.py
metavariant/exceptions.py
metavariant/hgvs_samples.py
metavariant/lovd.py
metavariant/lvg.py
metavariant/utils.py
metavariant.egg-info/PKG-INFO
metavariant.egg-info/SOURCES.txt
metavariant.egg-info/dependency_links.txt
metavariant.egg-info/requires.txt
metavariant.egg-info/top_level.txt