Metadata-Version: 2.1
Name: metavariant
Version: 0.1.3
Summary: a lexical manipulation toolkit for genetic variant descriptors (hgvs, etc)
Home-page: UNKNOWN
Author: Naomi Most
Author-email: naomi@nthmost.com
Maintainer: Naomi Most
Maintainer-email: naomi@nthmost.com
License: Apache 2.0
Platform: UNKNOWN
